slashcommands/__init__.py
slashcommands/errors.py
slashcommands/slashcommands.py
slashcommands-0.4.dist-info/METADATA
slashcommands-0.4.dist-info/RECORD
slashcommands-0.4.dist-info/WHEEL
slashcommands-0.4.dist-info/top_level.txt
