Metadata-Version: 2.1
Name: slashcommands
Version: 0.4
Summary: A tiny framework for slash commands of Slack.
Home-page: https://github.com/matsub/slashcommands
Author: matsub
Author-email: matsub.rk@gmail.com
License: MIT
Platform: UNKNOWN
Requires-Python: >=3.6
Requires-Dist: sanic (==0.7.0)
